README.md
setup.cfg
setup.py
src/sqla_ext/__init__.py
src/sqla_ext/protocols.py
src/sqla_ext.egg-info/PKG-INFO
src/sqla_ext.egg-info/SOURCES.txt
src/sqla_ext.egg-info/dependency_links.txt
src/sqla_ext.egg-info/requires.txt
src/sqla_ext.egg-info/top_level.txt
src/sqla_ext/func/__init__.py
src/sqla_ext/func/datetime/__init__.py
src/sqla_ext/func/datetime/utc_now.py
src/sqla_ext/func/json/__init__.py
src/sqla_ext/func/json/agg.py
src/sqla_ext/func/json/build_object.py
src/sqla_ext/func/json/to_array.py
src/sqla_ext/inspect/__init__.py
src/sqla_ext/inspect/_to_core_table.py
src/sqla_ext/inspect/_to_schema_name.py
src/sqla_ext/inspect/_to_table_name.py
src/sqla_ext/types/__init__.py
src/sqla_ext/types/generic/__init__.py
src/sqla_ext/types/postgresql/__init__.py
src/sqla_ext/types/postgresql/citext.py