Metadata-Version: 2.1
Name: sqla-ext
Version: 0.0.5
Summary: SQLAlchemy Helpers
Home-page: https://github.com/olirice/sqla
Author: Oliver Rice
Author-email: oliver@oliverrice.com
License: MIT
Platform: UNKNOWN
Classifier: Development Status :: 4 - Beta
Classifier: Natural Language :: English
Classifier: Operating System :: OS Independent
Classifier: Programming Language :: Python
Classifier: Programming Language :: Python :: 3
Classifier: Programming Language :: Python :: 3.6
Classifier: Programming Language :: Python :: 3.7
Classifier: Programming Language :: Python :: 3.8
Provides-Extra: dev
Provides-Extra: docs
